eui.py
eui-1.0.4.dist-info/LICENSE
eui-1.0.4.dist-info/METADATA
eui-1.0.4.dist-info/WHEEL
eui-1.0.4.dist-info/top_level.txt
eui-1.0.4.dist-info/RECORD
