Metadata-Version: 2.1
Name: eui
Version: 1.0.4
Summary: a fast and simple micro-framework for small browser-based application
Home-page: https://gitee.com/lixkhao/eui
Author: Li Xiangkui
Author-email: 1749498702@qq.com
License: MIT Licence
Keywords: pip,eui
Platform: any
